{
    "fabric:load_conditions": [
        {
            "condition": "fabric:all_mods_loaded",
            "values": [
                "create",
                "majruszsdifficulty",
                "create_simple_ore_doubling"
            ]
        }
    ],
    "type": "create:compacting",
    "heatRequirement": "superheated",
    "ingredients": [
        {
            "item": "majruszsdifficulty:enderium_shard"
        }
    ],
    "results": [
        {
            "count": 3,
            "item": "createmetalwork:crushed_enderium_shard"
        },
        {
            "chance": 0.15,
            "item": "create_simple_ore_doubling:slag"
        }
    ]
}